[
  {
    "name": "Telescope Dummy"
  , "server": "dummy"
  , "port": 4000
  , "telescope-device": "/dev/null"
  , "telescope-type": "dummy"
  },
  {
    "name": "Telescope Stellarium Dummy"
  , "server": "stellarium"
  , "port": 4001
  , "telescope-device": "/dev/random"
  , "telescope-type": "dummy"

  , "enabled": true
  },
  {
    "name": "Telescope Nextar"
  , "server": "web"
  , "port": 4002
  , "telescope-device": "/dev/ttyS00"
  , "telescope-type": "nextar"
  , "camera-device": "/dev/null"

  , "enabled": false
  }
]
